pskc/__init__.py
pskc/algorithms.py
pskc/device.py
pskc/encryption.py
pskc/exceptions.py
pskc/key.py
pskc/mac.py
pskc/parser.py
pskc/policy.py
pskc/serialiser.py
pskc/signature.py
pskc/xml.py
pskc/crypto/__init__.py
pskc/crypto/aeskw.py
pskc/crypto/tripledeskw.py
pskc/scripts/__init__.py
pskc/scripts/csv2pskc.py
pskc/scripts/pskc2csv.py
pskc/scripts/pskc2pskc.py
pskc/scripts/util.py
python_pskc-1.3.dist-info/COPYING
python_pskc-1.3.dist-info/METADATA
python_pskc-1.3.dist-info/WHEEL
python_pskc-1.3.dist-info/entry_points.txt
python_pskc-1.3.dist-info/top_level.txt
python_pskc-1.3.dist-info/RECORD
