Metadata-Version: 2.1
Name: python-pskc
Version: 1.3
Summary: Python module for handling PSKC files
Home-page: https://arthurdejong.org/python-pskc/
Author: Arthur de Jong
Author-email: arthur@arthurdejong.org
License: LGPL
Keywords: PSKC,RFC 6030,key container
Classifier: Development Status :: 5 - Production/Stable
Classifier: Intended Audience :: Developers
Classifier: Intended Audience :: Information Technology
Classifier: Intended Audience :: System Administrators
Classifier: License :: OSI Approved :: GNU Lesser General Public License v2 or later (LGPLv2+)
Classifier: Operating System :: OS Independent
Classifier: Programming Language :: Python
Classifier: Programming Language :: Python :: 3
Classifier: Programming Language :: Python :: 3.6
Classifier: Programming Language :: Python :: 3.7
Classifier: Programming Language :: Python :: 3.8
Classifier: Programming Language :: Python :: 3.9
Classifier: Programming Language :: Python :: 3.10
Classifier: Programming Language :: Python :: 3.11
Classifier: Programming Language :: Python :: 3.12
Classifier: Programming Language :: Python :: Implementation :: PyPy
Classifier: Topic :: Security :: Cryptography
Classifier: Topic :: Software Development :: Libraries :: Python Modules
Classifier: Topic :: System :: Systems Administration :: Authentication/Directory
Classifier: Topic :: Text Processing :: Markup :: XML
License-File: COPYING
Requires-Dist: cryptography
Requires-Dist: python-dateutil
Provides-Extra: defuse
Requires-Dist: defusedxml; extra == "defuse"
Provides-Extra: lxml
Requires-Dist: lxml; extra == "lxml"
Provides-Extra: signature
Requires-Dist: signxml; extra == "signature"
